[
	{
		"index":0,
		"found":false,
		"category":"actionable",
		"problem":{"CodeSnippet":"False"},
		"title":"Provide sample code and data"
	},
	{
		"index":1,
		"found":false,		
		"category":"actionable",
		"problem":{"BodyLength":"Medium","BodyLength":"Long"},
		"title":"Be concise"
	},
	{
		"index":2,
		"found":false,
		"category":"actionable",
		"problem":{"SentimentPositiveScore":"True","SentimentNegativeScore":"True"},
		"title":"Use a neutral emotional style"
	},
	{
		"index":3,
		"found":false,
		"category":"not_actionable",
		"problem":{"GMTHour":"Morning"},
		"title":"You're posting in the Morning."
	},
	{
		"index":4,
		"found":false,
		"category":"not_actionable",
		"problem":{"GMTHour":"Afternoon"},
		"title":"You're posting in the Afternoon."
	},
	{
		"index":5,
		"found":false,
		"category":"actionable",
		"problem":{"AvgUpperCharsPPostDisc":"High"},
		"title":"Use capital letters where appropriate"
	}								
]
